bulletroulette/CLIold.py
bulletroulette/__init__.py
bulletroulette/data.py
bulletroulette/dev.py
bulletroulette/roles.py
bulletroulette/run.py
bulletroulette/runCLI.py
bulletroulette/runGUI.py
bulletroulette/sprites.py
bulletroulette/assets/A.png
bulletroulette/assets/B.png
bulletroulette/assets/C.png
bulletroulette/assets/D.png
bulletroulette/assets/DELETE.png
bulletroulette/assets/E.png
bulletroulette/assets/ENTER.png
bulletroulette/assets/F.png
bulletroulette/assets/G.png
bulletroulette/assets/H.png
bulletroulette/assets/I.png
bulletroulette/assets/J.png
bulletroulette/assets/K.png
bulletroulette/assets/L.png
bulletroulette/assets/M.png
bulletroulette/assets/N.png
bulletroulette/assets/O.png
bulletroulette/assets/P.png
bulletroulette/assets/Q.png
bulletroulette/assets/R.png
bulletroulette/assets/S.png
bulletroulette/assets/Simhei.ttf
bulletroulette/assets/T.png
bulletroulette/assets/TV.png
bulletroulette/assets/TVvolta.png
bulletroulette/assets/U.png
bulletroulette/assets/V.png
bulletroulette/assets/W.png
bulletroulette/assets/X.png
bulletroulette/assets/Y.png
bulletroulette/assets/Z.png
bulletroulette/assets/__init__.py
bulletroulette/assets/beer.png
bulletroulette/assets/bg.png
bulletroulette/assets/bgmsc.ogg
bulletroulette/assets/binary.png
bulletroulette/assets/blank.png
bulletroulette/assets/blank.wav
bulletroulette/assets/boom.png
bulletroulette/assets/charge.png
bulletroulette/assets/dealershootplayer.png
bulletroulette/assets/dealershootself.png
bulletroulette/assets/dusebeer.png
bulletroulette/assets/dusehandcuff.png
bulletroulette/assets/duseknife.png
bulletroulette/assets/dusemagnifier.png
bulletroulette/assets/dusesmoke.png
bulletroulette/assets/gun.png
bulletroulette/assets/handcuff.png
bulletroulette/assets/knife.png
bulletroulette/assets/livedealer.wav
bulletroulette/assets/liveplayer.wav
bulletroulette/assets/liveround.png
bulletroulette/assets/magnifier.png
bulletroulette/assets/noneprop.png
bulletroulette/assets/pill.png
bulletroulette-1.1.1.dist-info/LICENSE
bulletroulette-1.1.1.dist-info/METADATA
bulletroulette-1.1.1.dist-info/WHEEL
bulletroulette-1.1.1.dist-info/top_level.txt
bulletroulette-1.1.1.dist-info/RECORD
