Metadata-Version: 2.1
Name: bulletroulette
Version: 1.1.1
Summary: Imitate game "Buskshot Roulette"
Home-page: https://github.com/BinaryGuo/Bullet_Roulette
Author: GQX
Author-email: kill114514251@outlook.com
Classifier: Intended Audience :: End Users/Desktop
Classifier: Development Status :: 3 - Alpha
Classifier: Topic :: Software Development :: Libraries :: pygame
Classifier: Natural Language :: Chinese (Simplified)
Classifier: License :: OSI Approved :: MIT License
Classifier: Operating System :: OS Independent
Classifier: Programming Language :: Python :: 3.13
Classifier: Programming Language :: Python :: 3.12
Classifier: Programming Language :: Python :: 3.11
Classifier: Programming Language :: Python :: 3.10
Classifier: Programming Language :: Python :: 3.9
Classifier: Programming Language :: Python :: 3.8
Requires-Python: >=3.8
License-File: LICENSE
Requires-Dist: pygame >=2.0.1
